llama_index/py.typed
llama_index/vector_stores/yugabytedb/__init__.py
llama_index/vector_stores/yugabytedb/base.py
llama_index_vector_stores_yugabytedb-0.5.4.dist-info/METADATA
llama_index_vector_stores_yugabytedb-0.5.4.dist-info/WHEEL
llama_index_vector_stores_yugabytedb-0.5.4.dist-info/licenses/LICENSE
llama_index_vector_stores_yugabytedb-0.5.4.dist-info/RECORD
