Metadata-Version: 2.4
Name: llama-index-vector-stores-yugabytedb
Version: 0.5.4
Summary: llama-index vector_stores yugabytedb integration
Author-email: YugabyteDB <pypi@yugabyte.com>
License-Expression: MIT
License-File: LICENSE
Requires-Python: <4.0,>=3.9
Requires-Dist: asyncpg<1.0.0,>=0.29.0
Requires-Dist: llama-index-core<0.13,>=0.12.6
Requires-Dist: pgvector<1.0.0,>=0.3.6
Requires-Dist: psycopg2-yugabytedb>=2.9.3.5
Requires-Dist: sqlalchemy-yugabytedb>=1.0.0.1
Requires-Dist: sqlalchemy[asyncio]<2.1,>=1.4.49
